olm_lib/__init__.py
olm_lib/events/__init__.py
olm_lib/events/event_producer.py
olm_lib/events/event_receiver.py
olm_lib/events/exchange_producer.py
olm_lib/events/exchange_receiver.py
olm_lib/logger/__init__.py
olm_lib/logger/logger_helper.py
olm_lib/main.py
olm_lib/workflow/__init__.py
olm_lib/workflow/workflow_helper.py
olm_lib-0.1.0.dist-info/METADATA
olm_lib-0.1.0.dist-info/WHEEL
olm_lib-0.1.0.dist-info/RECORD
