Metadata-Version: 2.1
Name: olm-lib
Version: 0.1.0
Summary: 
Author: hamzakitsys
Author-email: 33630482+hamzakalid@users.noreply.github.com
Requires-Python: >=3.11,<4.0
Classifier: Programming Language :: Python :: 3
Classifier: Programming Language :: Python :: 3.11
Classifier: Programming Language :: Python :: 3.12
Requires-Dist: pika (>=1.3.2,<2.0.0)
Requires-Dist: requests (>=2.31.0,<3.0.0)
